{
    "date": "2025-02-20",
    "location": [
        "北京市",
        "中国"
    ],
    "industry": [
        "国际贸易",
        "金融"
    ],
    "source": "新华网",
    "genre": "消息",
    "keywords": [
        "对等关税",
        "关税战",
        "多边贸易体制",
        "商务部",
        "中美贸易",
        "全球供应链"
    ],
    "subject": "中国商务部",
    "object": "美拟实施‘对等关税’回应",
    "action": "作出回应",
    "entity_triplet": "中国商务部,作出回应,美拟实施‘对等关税’",
    "authoritative_info": "美方提出的‘对等关税’做法被指严重破坏以最惠国待遇为基础的多边贸易体制；中方敦促美方不要动辄挥舞‘关税大棒’，通过平等磋商解决问题。",
    "data_evidence": "",
    "event_context": "2025年2月20日，中国商务部新闻发言人何亚东在例行新闻发布会上回应美国总统特朗普签署的‘对等关税’备忘录。中方指出美方行为违背世贸组织规则，破坏多边贸易体制平衡，强调关税战无出路且无赢家，并敦促美方纠正错误做法。",
    "impact_scope": "影响范围: 国际级",
    "stakeholders": [
        "涉及方: 中国商务部",
        "涉及方: 美国政府",
        "受益: 多边贸易体制",
        "涉及方: 世界贸易组织（WTO）",
        "涉及方: 全球供应链相关国家"
    ]
}