{
    "date": "2025-06-27",
    "location": [
        "浙江省",
        "中国"
    ],
    "industry": [
        "科技",
        "国际贸易"
    ],
    "source": "浙江日报",
    "genre": "消息",
    "keywords": [
        "新能源汽车出口",
        "出口额增长86%",
        "多元化市场",
        "中国—东盟自贸协定",
        "关税减免",
        "品牌知名度提升"
    ],
    "subject": "浙江省",
    "object": "新能源汽车出口加速",
    "action": "加速",
    "entity_triplet": "浙江省, 加速, 新能源汽车出口",
    "authoritative_info": "杭州海关发布的新能源汽车出口统计数据；‘中国—东盟自贸协定原产地证书’政策；‘新能源汽车出口一体化通关’新模式。",
    "data_evidence": "2025年前5月浙江省新能源汽车出口额达163.2亿元，同比增长86%；对欧盟、中东、东盟和拉美出口分别增长1.5倍、98.2%、3.9倍和1.4倍；温州企业首次向巴西出口新能源车；吉利公司通过‘中国—东盟自贸协定原产地证书’享受5%的关税减免。",
    "event_context": "2025年前5月，浙江省新能源汽车出口额达163.2亿元，同比增长86%。出口市场多元化，对欧盟、中东、东盟和拉美出口分别增长1.5倍、98.2%、3.9倍和1.4倍。企业通过开拓哈萨克斯坦、乌兹别克斯坦、阿联酋等新兴市场及首次出口巴西实现增长。杭州海关数据显示，出口商面临交付时效和售后配件挑战，海关联合商务部门推广‘新能源汽车出口一体化通关’模式，支持企业应对难题。",
    "impact_scope": "影响范围: 国际级",
    "stakeholders": [
        "涉及方: 浙江省人民政府",
        "涉及方: 杭州海关/温州海关",
        "涉及方: 浙江新能源汽车企业（如吉利、温州誉泰进出口有限公司）",
        "受益: 中国—东盟自贸协定成员国",
        "涉及方: 中亚国家（哈萨克斯坦、乌兹别克斯坦等）",
        "涉及方: 拉美市场（巴西）",
        "涉及方: 全球新能源汽车市场"
    ]
}